gambaterm/console.py
gambaterm/run.py
gambaterm/termblit.cpython-312-darwin.so
gambaterm/termblit.pyi
gambaterm/libgambatte.pyi
gambaterm/keyboard_input.py
gambaterm/__init__.py
gambaterm/ssh_app_session.py
gambaterm/libgambatte.cpython-312-darwin.so
gambaterm/file_input.py
gambaterm/py.typed
gambaterm/audio.py
gambaterm/controller_input.py
gambaterm/ssh.py
gambaterm/main.py
gambaterm/__main__.py
gambaterm/colors.py
gambaterm-0.13.2.dist-info/RECORD
gambaterm-0.13.2.dist-info/WHEEL
gambaterm-0.13.2.dist-info/entry_points.txt
gambaterm-0.13.2.dist-info/top_level.txt
gambaterm-0.13.2.dist-info/METADATA
gambaterm-0.13.2.dist-info/licenses/LICENSE
