Metadata-Version: 2.4
Name: gambaterm
Version: 0.13.2
Summary: A terminal frontend for gambatte game boy color emulator
Author-email: Vincent Michel <vxgmichel@gmail.com>
License-Expression: GPL-3.0-only
Project-URL: Homepage, https://github.com/vxgmichel/gambatte-terminal
Classifier: Programming Language :: Python
Classifier: Programming Language :: Python :: 3
Classifier: Programming Language :: Python :: 3.9
Classifier: Programming Language :: Python :: 3.10
Classifier: Programming Language :: Python :: 3.11
Classifier: Programming Language :: Python :: 3.12
Classifier: Programming Language :: Python :: 3.13
Classifier: Programming Language :: Python :: 3.14
Requires-Python: >=3.9
License-File: LICENSE
Requires-Dist: numpy<3.0.0,>=2.0.0
Requires-Dist: asyncssh<3.0.0,>=2.9
Requires-Dist: prompt_toolkit<4.0.0,>=3.0.29
Requires-Dist: sounddevice<1.0,>=0.4
Requires-Dist: samplerate<0.2.0,>=0.1.0
Requires-Dist: python-xlib; sys_platform == "linux"
Requires-Dist: pynput; sys_platform != "linux"
Provides-Extra: controller-support
Requires-Dist: pygame<2.0.0,>=1.9.5; extra == "controller-support"
Dynamic: license-file
